archive/setup.py
archive/tcp_gateway.py
examples/echo_cmdline_client.py
examples/simple_echo_client.py
examples/simple_echo_server.py
examples/single.py
examples/tk_echo_client.py
examples/banyan_base_multi/multi_driver.py
examples/banyan_base_multi/simple_demo/multi_echo_server.py
examples/banyan_base_multi/simple_demo/notifier.py
examples/ecs/setup.py
examples/ecs/ecs/__init__.py
examples/ecs/ecs/echo_cmdline_client.py
examples/ecs/ecs/echo_cmdline_server.py
examples/ecs/ecs/tk_echo_client.py
examples/mqtt_gateway/bpub.py
examples/mqtt_gateway/bsub.py
examples/mqtt_gateway/pub.py
examples/mqtt_gateway/sub.py
holding/banyan_base_aio.py
holding/gateway_base_aio.py
holding/ls.py
holding/ls2.py
holding/telemetrix_aio.py
projects/OneGPIO/arduino_uno/__init__.py
projects/OneGPIO/arduino_uno/arduino_gateway.py
projects/OneGPIO/arduino_uno/arduino_gatewayORIG.py
projects/OneGPIO/esp32_gateway/__init__.py
projects/OneGPIO/esp32_gateway/esp32_gateway.py
projects/OneGPIO/esp32_gateway/simple_echo_client.py
projects/OneGPIO/esp_8266/__init__.py
projects/OneGPIO/esp_8266/esp8266_gateway.py
projects/OneGPIO/esp_8266/esp_8266.py
projects/OneGPIO/esp_8266/esp_8266_micropython/esp_8266Full.py
projects/OneGPIO/raspberry_pi/__init__.py
projects/OneGPIO/raspberry_pi/rpi_gateway.py
projects/OneGPIO/raspberry_pi/servo.py
projects/OneGPIO/raspberry_pi/sonar.py
projects/OneGPIO/raspberry_pi/stepper.py
projects/OneGPIO/shared/banyan_tkinter_demo.py
projects/OneGPIO/shared/blinker.py
projects/OneGPIO/shared/open_browser.py
projects/OneGPIO/shared/ws_gateway.py
python_banyan/__init__.py
python_banyan/backplane/__init__.py
python_banyan/backplane/backplane.py
python_banyan/banyan_base/__init__.py
python_banyan/banyan_base/banyan_base.py
python_banyan/banyan_base_aio/__init__.py
python_banyan/banyan_base_aio/banyan_base_aio.py
python_banyan/banyan_base_multi/__init__.py
python_banyan/banyan_base_multi/banyan_base_multi.py
python_banyan/gateway_base/__init__.py
python_banyan-3.16.dist-info/LICENSE
python_banyan-3.16.dist-info/METADATA
python_banyan-3.16.dist-info/WHEEL
python_banyan-3.16.dist-info/entry_points.txt
python_banyan-3.16.dist-info/top_level.txt
python_banyan-3.16.dist-info/RECORD
