Metadata-Version: 2.1
Name: python_banyan
Version: 3.16
Summary: The Python Banyan Framework
Author-email: Alan Yorinks <MisterYsLab@gmail.com>
License: AGPL-3.0-or-later
Keywords: python banyan,RPC,Remote Procedure Call,Event Driven,Asynchronous,Non-Blocking,Raspberry Pi,ZeroMQ,MessagePack,RedBot
Classifier: Development Status :: 5 - Production/Stable
Classifier: Environment :: Other Environment
Classifier: Intended Audience :: Developers
Classifier: Intended Audience :: Education
Classifier: Operating System :: OS Independent
Classifier: Topic :: Software Development :: Libraries :: Python Modules
Requires-Python: >=3.8
License-File: LICENSE
Requires-Dist: pyzmq
Requires-Dist: msgpack-python
Requires-Dist: numpy>=1.9
Requires-Dist: msgpack-numpy
Requires-Dist: psutil
Requires-Dist: apscheduler
Requires-Dist: websockets==13.1
